BoardTester-1.0.1.dist-info/top_level.txt
BoardTester-1.0.1.dist-info/DESCRIPTION.rst
BoardTester-1.0.1.dist-info/METADATA
BoardTester-1.0.1.dist-info/metadata.json
BoardTester-1.0.1.dist-info/WHEEL
BoardTester-1.0.1.dist-info/RECORD
boardtester/process.py
boardtester/broaster.py
boardtester/camids.py
boardtester/visualize.py
boardtester/__init__.py
