Metadata-Version: 2.0
Name: BoardTester
Version: 1.0.1
Summary: collect data with automated hardware power cycling
Home-page: https://github.com/nharringtonwasatch/BoardTester
Author: Nathan Harrington
Author-email: nharrington@wasatchphotonics.com
License: UNKNOWN
Download-URL: https://github.com/nharringtonwasatch/BoardTester
Platform: UNKNOWN
Requires-Dist: phidgeter
Requires-Dist: wasatchusb
Requires-Dist: wpexam
Requires-Dist: colorama
Requires-Dist: wmi
Requires-Dist: natsort
